kafkaavro/__init__.py
kafkaavro/avro_datatypes.py
kafkaavro/data_governance.py
kafkaavro/impact_lineage.py
kafkaavro/rowtype.py
kafkaavro/schemabuilder.py
rtdi_kafkaavro-0.10.48.dist-info/METADATA
rtdi_kafkaavro-0.10.48.dist-info/WHEEL
rtdi_kafkaavro-0.10.48.dist-info/licenses/LICENSE
rtdi_kafkaavro-0.10.48.dist-info/RECORD
