Metadata-Version: 2.4
Name: rtdi_kafkaavro
Version: 0.10.48
Summary: Kafka schema support for data integration
Project-URL: Homepage, https://github.com/rtdi/KafkaAvro
Project-URL: Issues, https://github.com/rtdi/KafkaAvro/issues
Author-email: Werner Dähn <werner.daehn@rtdi.io>
License-Expression: Apache-2.0
License-File: LICENSE
Classifier: Operating System :: OS Independent
Classifier: Programming Language :: Python :: 3
Requires-Python: >=3.9
Requires-Dist: avro
Requires-Dist: jsonpickle
Requires-Dist: pyarrow
